Metadata-Version: 1.1
Name: mandrill-python
Version: 1.1.0
Summary: Fork of the original CLI client and Python API library for the Mandrill email as a service platform.
Home-page: https://bitbucket.org/mailchimp/mandrill-python-fork/
Author: Mandrill Devs
Author-email: community@mandrill.com
License: Apache-2.0
Keywords: mandrill email api
Platform: UNKNOWN
Classifier: Development Status :: 4 - Beta
Classifier: Environment :: Console
Classifier: Intended Audience :: Developers
Classifier: Intended Audience :: System Administrators
Classifier: License :: OSI Approved :: Apache Software License
Classifier: Topic :: Communications :: Email
